[
{"name": "China", "population": "1,439,323,776", "area": "9,388,211"},
{"name": "India", "population": "1,380,004,385", "area": "2,973,190"},
{"name": "United States", "population": "331,002,651", "area": "9,147,420"},
{"name": "Indonesia", "population": "273,523,615", "area": "1,811,570"},
{"name": "Pakistan", "population": "220,892,340", "area": "770,880"},
{"name": "Brazil", "population": "212,559,417", "area": "8,358,140"},
{"name": "Nigeria", "population": "206,139,589", "area": "910,770"},
{"name": "Bangladesh", "population": "164,689,383", "area": "130,170"},
{"name": "Russia", "population": "145,934,462", "area": "16,376,870"},
{"name": "Mexico", "population": "128,932,753", "area": "1,943,950"},
{"name": "Japan", "population": "126,476,461", "area": "364,555"},
{"name": "Ethiopia", "population": "114,963,588", "area": "1,000,000"},
{"name": "Philippines", "population": "109,581,078", "area": "298,170"},
{"name": "Egypt", "population": "102,334,404", "area": "995,450"},
{"name": "Vietnam", "population": "97,338,579", "area": "310,070"},
{"name": "DR Congo", "population": "89,561,403", "area": "2,267,050"},
{"name": "Turkey", "population": "84,339,067", "area": "769,630"},
{"name": "Iran", "population": "83,992,949", "area": "1,628,550"},
{"name": "Germany", "population": "83,783,942", "area": "348,560"},
{"name": "Thailand", "population": "69,799,978", "area": "510,890"},
{"name": "United Kingdom", "population": "67,886,011", "area": "241,930"},
{"name": "France", "population": "65,273,511", "area": "547,557"},
{"name": "Italy", "population": "60,461,826", "area": "294,140"},
{"name": "Tanzania", "population": "59,734,218", "area": "885,800"},
{"name": "South Africa", "population": "59,308,690", "area": "1,213,090"},
{"name": "Myanmar", "population": "54,409,800", "area": "653,290"},
{"name": "Kenya", "population": "53,771,296", "area": "569,140"},
{"name": "South Korea", "population": "51,269,185", "area": "97,230"},
{"name": "Colombia", "population": "50,882,891", "area": "1,109,500"},
{"name": "Spain", "population": "46,754,778", "area": "498,800"},
{"name": "Uganda", "population": "45,741,007", "area": "199,810"},
{"name": "Argentina", "population": "45,195,774", "area": "2,736,690"},
{"name": "Algeria", "population": "43,851,044", "area": "2,381,740"},
{"name": "Sudan", "population": "43,849,260", "area": "1,765,048"},
{"name": "Ukraine", "population": "43,733,762", "area": "579,320"},
{"name": "Iraq", "population": "40,222,493", "area": "434,320"},
{"name": "Afghanistan", "population": "38,928,346", "area": "652,860"},
{"name": "Poland", "population": "37,846,611", "area": "306,230"},
{"name": "Canada", "population": "37,742,154", "area": "9,093,510"},
{"name": "Morocco", "population": "36,910,560", "area": "446,300"},
{"name": "Saudi Arabia", "population": "34,813,871", "area": "2,149,690"},
{"name": "Uzbekistan", "population": "33,469,203", "area": "425,400"},
{"name": "Peru", "population": "32,971,854", "area": "1,280,000"},
{"name": "Angola", "population": "32,866,272", "area": "1,246,700"},
{"name": "Malaysia", "population": "32,365,999", "area": "328,550"},
{"name": "Mozambique", "population": "31,255,435", "area": "786,380"},
{"name": "Ghana", "population": "31,072,940", "area": "227,540"},
{"name": "Yemen", "population": "29,825,964", "area": "527,970"},
{"name": "Nepal", "population": "29,136,808", "area": "143,350"},
{"name": "Venezuela", "population": "28,435,940", "area": "882,050"},
{"name": "Madagascar", "population": "27,691,018", "area": "581,795"},
{"name": "Cameroon", "population": "26,545,863", "area": "472,710"},
{"name": "C\u00f4te d'Ivoire", "population": "26,378,274", "area": "318,000"},
{"name": "North Korea", "population": "25,778,816", "area": "120,410"},
{"name": "Australia", "population": "25,499,884", "area": "7,682,300"},
{"name": "Niger", "population": "24,206,644", "area": "1,266,700"},
{"name": "Taiwan", "population": "23,816,775", "area": "35,410"},
{"name": "Sri Lanka", "population": "21,413,249", "area": "62,710"},
{"name": "Burkina Faso", "population": "20,903,273", "area": "273,600"},
{"name": "Mali", "population": "20,250,833", "area": "1,220,190"},
{"name": "Romania", "population": "19,237,691", "area": "230,170"},
{"name": "Malawi", "population": "19,129,952", "area": "94,280"},
{"name": "Chile", "population": "19,116,201", "area": "743,532"},
{"name": "Kazakhstan", "population": "18,776,707", "area": "2,699,700"},
{"name": "Zambia", "population": "18,383,955", "area": "743,390"},
{"name": "Guatemala", "population": "17,915,568", "area": "107,160"},
{"name": "Ecuador", "population": "17,643,054", "area": "248,360"},
{"name": "Syria", "population": "17,500,658", "area": "183,630"},
{"name": "Netherlands", "population": "17,134,872", "area": "33,720"},
{"name": "Senegal", "population": "16,743,927", "area": "192,530"},
{"name": "Cambodia", "population": "16,718,965", "area": "176,520"},
{"name": "Chad", "population": "16,425,864", "area": "1,259,200"},
{"name": "Somalia", "population": "15,893,222", "area": "627,340"},
{"name": "Zimbabwe", "population": "14,862,924", "area": "386,850"},
{"name": "Guinea", "population": "13,132,795", "area": "245,720"},
{"name": "Rwanda", "population": "12,952,218", "area": "24,670"},
{"name": "Benin", "population": "12,123,200", "area": "112,760"},
{"name": "Burundi", "population": "11,890,784", "area": "25,680"},
{"name": "Tunisia", "population": "11,818,619", "area": "155,360"},
{"name": "Bolivia", "population": "11,673,021", "area": "1,083,300"},
{"name": "Belgium", "population": "11,589,623", "area": "30,280"},
{"name": "Haiti", "population": "11,402,528", "area": "27,560"},
{"name": "Cuba", "population": "11,326,616", "area": "106,440"},
{"name": "South Sudan", "population": "11,193,725", "area": "610,952"},
{"name": "Dominican Republic", "population": "10,847,910", "area": "48,320"},
{"name": "Czech Republic (Czechia)", "population": "10,708,981", "area": "77,240"},
{"name": "Greece", "population": "10,423,054", "area": "128,900"},
{"name": "Jordan", "population": "10,203,134", "area": "88,780"},
{"name": "Portugal", "population": "10,196,709", "area": "91,590"},
{"name": "Azerbaijan", "population": "10,139,177", "area": "82,658"},
{"name": "Sweden", "population": "10,099,265", "area": "410,340"},
{"name": "Honduras", "population": "9,904,607", "area": "111,890"},
{"name": "United Arab Emirates", "population": "9,890,402", "area": "83,600"},
{"name": "Hungary", "population": "9,660,351", "area": "90,530"},
{"name": "Tajikistan", "population": "9,537,645", "area": "139,960"},
{"name": "Belarus", "population": "9,449,323", "area": "202,910"},
{"name": "Austria", "population": "9,006,398", "area": "82,409"},
{"name": "Papua New Guinea", "population": "8,947,024", "area": "452,860"},
{"name": "Serbia", "population": "8,737,371", "area": "87,460"},
{"name": "Israel", "population": "8,655,535", "area": "21,640"},
{"name": "Switzerland", "population": "8,654,622", "area": "39,516"},
{"name": "Togo", "population": "8,278,724", "area": "54,390"},
{"name": "Sierra Leone", "population": "7,976,983", "area": "72,180"},
{"name": "Hong Kong", "population": "7,496,981", "area": "1,050"},
{"name": "Laos", "population": "7,275,560", "area": "230,800"},
{"name": "Paraguay", "population": "7,132,538", "area": "397,300"},
{"name": "Bulgaria", "population": "6,948,445", "area": "108,560"},
{"name": "Libya", "population": "6,871,292", "area": "1,759,540"},
{"name": "Lebanon", "population": "6,825,445", "area": "10,230"},
{"name": "Nicaragua", "population": "6,624,554", "area": "120,340"},
{"name": "Kyrgyzstan", "population": "6,524,195", "area": "191,800"},
{"name": "El Salvador", "population": "6,486,205", "area": "20,720"},
{"name": "Turkmenistan", "population": "6,031,200", "area": "469,930"},
{"name": "Singapore", "population": "5,850,342", "area": "700"},
{"name": "Denmark", "population": "5,792,202", "area": "42,430"},
{"name": "Finland", "population": "5,540,720", "area": "303,890"},
{"name": "Congo", "population": "5,518,087", "area": "341,500"},
{"name": "Slovakia", "population": "5,459,642", "area": "48,088"},
{"name": "Norway", "population": "5,421,241", "area": "365,268"},
{"name": "Oman", "population": "5,106,626", "area": "309,500"},
{"name": "State of Palestine", "population": "5,101,414", "area": "6,020"},
{"name": "Costa Rica", "population": "5,094,118", "area": "51,060"},
{"name": "Liberia", "population": "5,057,681", "area": "96,320"},
{"name": "Ireland", "population": "4,937,786", "area": "68,890"},
{"name": "Central African Republic", "population": "4,829,767", "area": "622,980"},
{"name": "New Zealand", "population": "4,822,233", "area": "263,310"},
{"name": "Mauritania", "population": "4,649,658", "area": "1,030,700"},
{"name": "Panama", "population": "4,314,767", "area": "74,340"},
{"name": "Kuwait", "population": "4,270,571", "area": "17,820"},
{"name": "Croatia", "population": "4,105,267", "area": "55,960"},
{"name": "Moldova", "population": "4,033,963", "area": "32,850"},
{"name": "Georgia", "population": "3,989,167", "area": "69,490"},
{"name": "Eritrea", "population": "3,546,421", "area": "101,000"},
{"name": "Uruguay", "population": "3,473,730", "area": "175,020"},
{"name": "Bosnia and Herzegovina", "population": "3,280,819", "area": "51,000"},
{"name": "Mongolia", "population": "3,278,290", "area": "1,553,560"},
{"name": "Armenia", "population": "2,963,243", "area": "28,470"},
{"name": "Jamaica", "population": "2,961,167", "area": "10,830"},
{"name": "Qatar", "population": "2,881,053", "area": "11,610"},
{"name": "Albania", "population": "2,877,797", "area": "27,400"},
{"name": "Puerto Rico", "population": "2,860,853", "area": "8,870"},
{"name": "Lithuania", "population": "2,722,289", "area": "62,674"},
{"name": "Namibia", "population": "2,540,905", "area": "823,290"},
{"name": "Gambia", "population": "2,416,668", "area": "10,120"},
{"name": "Botswana", "population": "2,351,627", "area": "566,730"},
{"name": "Gabon", "population": "2,225,734", "area": "257,670"},
{"name": "Lesotho", "population": "2,142,249", "area": "30,360"},
{"name": "North Macedonia", "population": "2,083,374", "area": "25,220"},
{"name": "Slovenia", "population": "2,078,938", "area": "20,140"},
{"name": "Guinea-Bissau", "population": "1,968,001", "area": "28,120"},
{"name": "Latvia", "population": "1,886,198", "area": "62,200"},
{"name": "Bahrain", "population": "1,701,575", "area": "760"},
{"name": "Equatorial Guinea", "population": "1,402,985", "area": "28,050"},
{"name": "Trinidad and Tobago", "population": "1,399,488", "area": "5,130"},
{"name": "Estonia", "population": "1,326,535", "area": "42,390"},
{"name": "Timor-Leste", "population": "1,318,445", "area": "14,870"},
{"name": "Mauritius", "population": "1,271,768", "area": "2,030"},
{"name": "Cyprus", "population": "1,207,359", "area": "9,240"},
{"name": "Eswatini", "population": "1,160,164", "area": "17,200"},
{"name": "Djibouti", "population": "988,000", "area": "23,180"},
{"name": "Fiji", "population": "896,445", "area": "18,270"},
{"name": "R\u00e9union", "population": "895,312", "area": "2,500"},
{"name": "Comoros", "population": "869,601", "area": "1,861"},
{"name": "Guyana", "population": "786,552", "area": "196,850"},
{"name": "Bhutan", "population": "771,608", "area": "38,117"},
{"name": "Solomon Islands", "population": "686,884", "area": "27,990"},
{"name": "Macao", "population": "649,335", "area": "30"},
{"name": "Montenegro", "population": "628,066", "area": "13,450"},
{"name": "Luxembourg", "population": "625,978", "area": "2,590"},
{"name": "Western Sahara", "population": "597,339", "area": "266,000"},
{"name": "Suriname", "population": "586,632", "area": "156,000"},
{"name": "Cabo Verde", "population": "555,987", "area": "4,030"},
{"name": "Maldives", "population": "540,544", "area": "300"},
{"name": "Malta", "population": "441,543", "area": "320"},
{"name": "Brunei ", "population": "437,479", "area": "5,270"},
{"name": "Guadeloupe", "population": "400,124", "area": "1,690"},
{"name": "Belize", "population": "397,628", "area": "22,810"},
{"name": "Bahamas", "population": "393,244", "area": "10,010"},
{"name": "Martinique", "population": "375,265", "area": "1,060"},
{"name": "Iceland", "population": "341,243", "area": "100,250"},
{"name": "Vanuatu", "population": "307,145", "area": "12,190"},
{"name": "French Guiana", "population": "298,682", "area": "82,200"},
{"name": "Barbados", "population": "287,375", "area": "430"},
{"name": "New Caledonia", "population": "285,498", "area": "18,280"},
{"name": "French Polynesia", "population": "280,908", "area": "3,660"},
{"name": "Mayotte", "population": "272,815", "area": "375"},
{"name": "Sao Tome & Principe", "population": "219,159", "area": "960"},
{"name": "Samoa", "population": "198,414", "area": "2,830"},
{"name": "Saint Lucia", "population": "183,627", "area": "610"},
{"name": "Channel Islands", "population": "173,863", "area": "190"},
{"name": "Guam", "population": "168,775", "area": "540"},
{"name": "Cura\u00e7ao", "population": "164,093", "area": "444"},
{"name": "Kiribati", "population": "119,449", "area": "810"},
{"name": "Micronesia", "population": "115,023", "area": "700"},
{"name": "Grenada", "population": "112,523", "area": "340"},
{"name": "St. Vincent & Grenadines", "population": "110,940", "area": "390"},
{"name": "Aruba", "population": "106,766", "area": "180"},
{"name": "Tonga", "population": "105,695", "area": "720"},
{"name": "U.S. Virgin Islands", "population": "104,425", "area": "350"},
{"name": "Seychelles", "population": "98,347", "area": "460"},
{"name": "Antigua and Barbuda", "population": "97,929", "area": "440"},
{"name": "Isle of Man", "population": "85,033", "area": "570"},
{"name": "Andorra", "population": "77,265", "area": "470"},
{"name": "Dominica", "population": "71,986", "area": "750"},
{"name": "Cayman Islands", "population": "65,722", "area": "240"},
{"name": "Bermuda", "population": "62,278", "area": "50"},
{"name": "Marshall Islands", "population": "59,190", "area": "180"},
{"name": "Northern Mariana Islands", "population": "57,559", "area": "460"},
{"name": "Greenland", "population": "56,770", "area": "410,450"},
{"name": "American Samoa", "population": "55,191", "area": "200"},
{"name": "Saint Kitts & Nevis", "population": "53,199", "area": "260"},
{"name": "Faeroe Islands", "population": "48,863", "area": "1,396"},
{"name": "Sint Maarten", "population": "42,876", "area": "34"},
{"name": "Monaco", "population": "39,242", "area": "1"},
{"name": "Turks and Caicos", "population": "38,717", "area": "950"},
{"name": "Saint Martin", "population": "38,666", "area": "53"},
{"name": "Liechtenstein", "population": "38,128", "area": "160"},
{"name": "San Marino", "population": "33,931", "area": "60"},
{"name": "Gibraltar", "population": "33,691", "area": "10"},
{"name": "British Virgin Islands", "population": "30,231", "area": "150"},
{"name": "Caribbean Netherlands", "population": "26,223", "area": "328"},
{"name": "Palau", "population": "18,094", "area": "460"},
{"name": "Cook Islands", "population": "17,564", "area": "240"},
{"name": "Anguilla", "population": "15,003", "area": "90"},
{"name": "Tuvalu", "population": "11,792", "area": "30"},
{"name": "Wallis & Futuna", "population": "11,239", "area": "140"},
{"name": "Nauru", "population": "10,824", "area": "20"},
{"name": "Saint Barthelemy", "population": "9,877", "area": "21"},
{"name": "Saint Helena", "population": "6,077", "area": "390"},
{"name": "Saint Pierre & Miquelon", "population": "5,794", "area": "230"},
{"name": "Montserrat", "population": "4,992", "area": "100"},
{"name": "Falkland Islands", "population": "3,480", "area": "12,170"},
{"name": "Niue", "population": "1,626", "area": "260"},
{"name": "Tokelau", "population": "1,357", "area": "10"},
{"name": "Holy See", "population": "801", "area": "0"}
]